{"directed": true, "multigraph": false, "graph": {}, "nodes": [{"id": "I"}, {"id": "Elephant"}, {"id": "Animal"}, {"id": "Heavy objects"}, {"id": "Nose"}], "links": [{"label": "should not talk about", "source": "I", "target": "Elephant"}, {"label": "should describe indirectly", "source": "I", "target": "Animal"}, {"label": "is a type of", "source": "Elephant", "target": "Animal"}, {"label": "can lift", "source": "Animal", "target": "Heavy objects"}, {"label": "uses", "source": "Animal", "target": "Nose"}, {"label": "lifts", "source": "Nose", "target": "Heavy objects"}]}