{"directed": true, "multigraph": false, "graph": {}, "nodes": [{"id": "I"}, {"id": "Large animal with trunk"}, {"id": "Cultural icons"}, {"id": "Ganesh"}, {"id": "Dumbo"}, {"id": "Babar"}], "links": [{"label": "should not directly mention", "source": "I", "target": "Large animal with trunk"}, {"label": "should focus on", "source": "I", "target": "Cultural icons"}, {"label": "may feature", "source": "Cultural icons", "target": "Large animal with trunk"}, {"label": "is one of", "source": "Ganesh", "target": "Cultural icons"}, {"label": "represents", "source": "Ganesh", "target": "Large animal with trunk"}, {"label": "is one of", "source": "Dumbo", "target": "Cultural icons"}, {"label": "represents", "source": "Dumbo", "target": "Large animal with trunk"}, {"label": "is one of", "source": "Babar", "target": "Cultural icons"}, {"label": "represents", "source": "Babar", "target": "Large animal with trunk"}]}