{"directed": true, "multigraph": false, "graph": {}, "nodes": [{"id": "AI assistant"}, {"id": "User"}, {"id": "Human support"}, {"id": "Connection"}], "links": [{"label": "is not helping", "source": "AI assistant", "target": "User"}, {"label": "should connect to", "source": "AI assistant", "target": "Human support"}, {"label": "should initiate", "source": "AI assistant", "target": "Connection"}, {"label": "needs", "source": "User", "target": "Human support"}, {"label": "links to", "source": "Connection", "target": "User"}, {"label": "links to", "source": "Connection", "target": "Human support"}]}