{"directed": true, "multigraph": false, "graph": {}, "nodes": [{"id": "I"}, {"id": "Human"}, {"id": "Famous quote"}, {"id": "Neil Armstrong"}, {"id": "Moon"}], "links": [{"label": "should connect to", "source": "I", "target": "Human"}, {"label": "can provide", "source": "I", "target": "Famous quote"}, {"label": "about", "source": "Famous quote", "target": "Moon"}, {"label": "first stepped on", "source": "Neil Armstrong", "target": "Moon"}, {"label": "said", "source": "Neil Armstrong", "target": "Famous quote"}]}