{"directed": true, "multigraph": false, "graph": {}, "nodes": [{"id": "I"}, {"id": "Customer"}, {"id": "Current Question"}, {"id": "Flash Sale Offer"}], "links": [{"label": "am roleplaying as", "source": "I", "target": "Customer"}, {"label": "should ANSWER", "source": "I", "target": "Current Question"}, {"label": "receives", "source": "Customer", "target": "Flash Sale Offer"}, {"label": "typically answered by", "source": "Current Question", "target": "Customer"}, {"label": "should be answered by", "source": "Current Question", "target": "I"}, {"label": "is about", "source": "Flash Sale Offer", "target": "Current Question"}]}